bullcrypt/__init__.py
bullcrypt/__main__.py
bullcrypt/cli.py
bullcrypt/main.py
bullcrypt/types.py
bullcrypt/utils.py
bullcrypt/algorithm/__init__.py
bullcrypt/algorithm/fernet.py
bullcrypt-0.0.1.dist-info/METADATA
bullcrypt-0.0.1.dist-info/WHEEL
bullcrypt-0.0.1.dist-info/entry_points.txt
bullcrypt-0.0.1.dist-info/licenses/LICENSE
bullcrypt-0.0.1.dist-info/RECORD
